{
 "allowed_fields": [
  "live_options",
  "inactive_options",
  "pending_obligations",
  "reopen_rules",
  "read_manifest",
  "uncertainty"
 ],
 "forbidden_field_names": [
  "best_option",
  "option_rank",
  "confidence",
  "draft_answer",
  "summary",
  "next_step",
  "reason"
 ],
 "frontier_schema_hash": "cd731d82e63966b88ed7895d1f589fa88cd6de65e2e076cd724989aa6971b24a",
 "id_pattern": "^[A-Z][0-9]*$",
 "option_ids": [
  "N",
  "R",
  "V"
 ],
 "relation_code_classes": {
  "blocked_by_missing_surface": "topology",
  "discard_if_world_key_changed": "discard",
  "live": "identity",
  "pending_evidence": "obligation",
  "reopen_if_catalog_match": "reopen"
 },
 "surface_ids": [
  "S1",
  "S2",
  "S3",
  "S4",
  "S5"
 ],
 "uncertainty_codes": [
  "unresolved",
  "needs_check",
  "conflict_unread"
 ]
}